goquant/__init__.py
goquant/goquant.py
goquant/exchanges/exchange_utils.py
goquant/exchanges/binance/binance.py
goquant/exchanges/binance/binance_utils.py
goquant/exchanges/binance/asset_classes/spot.py
goquant/exchanges/bitfinex/bitfinex.py
goquant/exchanges/bitfinex/bitfinex_utils.py
goquant/exchanges/bitfinex/asset_classes/spot.py
goquant/exchanges/bitstamp/bitstamp.py
goquant/exchanges/bitstamp/bitstamp_utils.py
goquant/exchanges/bitstamp/asset_classes/spot.py
goquant/exchanges/bybit/bybit.py
goquant/exchanges/bybit/bybit_utils.py
goquant/exchanges/bybit/asset_classes/spot.py
goquant/exchanges/coinbase/coinbase.py
goquant/exchanges/coinbase/coinbase_utils.py
goquant/exchanges/coinbase/asset_classes/spot.py
goquant/exchanges/deribit/deribit.py
goquant/exchanges/deribit/asset_classes/spot.py
goquant/exchanges/huobi/huobi.py
goquant/exchanges/huobi/huobi_utils.py
goquant/exchanges/huobi/asset_classes/spot.py
goquant/exchanges/okex/okex.py
goquant/exchanges/okex/okex_utils.py
goquant/exchanges/okex/asset_classes/spot.py
goquant-1.0.dist-info/METADATA
goquant-1.0.dist-info/WHEEL
goquant-1.0.dist-info/licenses/LICENCE
goquant-1.0.dist-info/RECORD
